syncrepl_client/__init__.py
syncrepl_client/_version.py
syncrepl_client/callbacks.py
syncrepl_client/exceptions.py
syncrepl_client-0.95.1.data/scripts/syncrepl-client
syncrepl_client-0.95.1.dist-info/DESCRIPTION.rst
syncrepl_client-0.95.1.dist-info/METADATA
syncrepl_client-0.95.1.dist-info/RECORD
syncrepl_client-0.95.1.dist-info/WHEEL
syncrepl_client-0.95.1.dist-info/metadata.json
syncrepl_client-0.95.1.dist-info/top_level.txt
syncrepl_client-0.95.1.dist-info/zip-safe
