Metadata-Version: 2.0
Name: syncrepl-client
Version: 0.95.1
Summary: An easier-to-use LDAP syncrepl client
Home-page: http://github.com/akkornel/syncrepl
Author: A. Karl Kornel
Author-email: karl@kornel.us
License: BSD 3-Clause
Keywords: ldap syncrepl
Platform: UNKNOWN
Classifier: Development Status :: 4 - Beta
Classifier: Environment :: Console
Classifier: Environment :: No Input/Output (Daemon)
Classifier: Intended Audience :: Developers
Classifier: Intended Audience :: System Administrators
Classifier: License :: OSI Approved :: BSD License
Classifier: Operating System :: MacOS :: MacOS X
Classifier: Operating System :: POSIX
Classifier: Operating System :: Unix
Classifier: Programming Language :: Python
Classifier: Programming Language :: Python :: 2.7
Classifier: Programming Language :: Python :: 3.3
Classifier: Programming Language :: Python :: 3.4
Classifier: Programming Language :: Python :: 3.5
Classifier: Programming Language :: Python :: 3.6
Classifier: Topic :: System :: Systems Administration :: Authentication/Directory :: LDAP
Provides: syncrepl_client
Requires-Python: >=2.7,!=3.0.*
Requires-Dist: pyasn1 (>=0.2.2,<0.3.1)
Requires-Dist: enum34; python_version<'3.4'
Requires-Dist: python-ldap (>=99); python_version<='2.7'
Requires-Dist: pyldap (>=2.4.37); python_version>='3.1'
